{
  "skorulis": [
    {
      "date": "2015-12-24",
      "count": "227"
    },
    {
      "date": "2015-12-25",
      "count": "228"
    },
    {
      "date": "2015-12-26",
      "count": "227"
    },
    {
      "date": "2015-12-27",
      "count": "228"
    },
    {
      "date": "2015-12-28",
      "count": "228"
    },
    {
      "date": "2015-12-29",
      "count": "234"
    },
    {
      "date": "2016-01-01",
      "count": "221"
    },
    {
      "date": "2016-01-02",
      "count": "223"
    },
    {
      "date": "2016-01-03",
      "count": "229"
    },
    {
      "date": "2016-01-04",
      "count": "224"
    },
    {
      "date": "2016-01-05",
      "count": "226"
    },
    {
      "date": "2016-01-06",
      "count": "249"
    },
    {
      "date": "2016-01-07",
      "count": "254"
    },
    {
      "date": "2016-01-08",
      "count": "256"
    },
    {
      "date": "2016-01-09",
      "count": "261"
    },
    {
      "date": "2016-01-10",
      "count": "263"
    },
    {
      "date": "2016-01-11",
      "count": "258"
    },
    {
      "date": "2016-01-12",
      "count": "259"
    },
    {
      "date": "2016-01-13",
      "count": "258"
    },
    {
      "date": "2016-01-14",
      "count": "250"
    },
    {
      "date": "2016-01-15",
      "count": "246"
    },
    {
      "date": "2016-01-16",
      "count": "241"
    },
    {
      "date": "2016-01-20",
      "count": "235"
    },
    {
      "date": "2016-01-21",
      "count": "231"
    },
    {
      "date": "2016-01-22",
      "count": "230"
    },
    {
      "date": "2016-01-23",
      "count": "228"
    },
    {
      "date": "2016-01-25",
      "count": "225"
    },
    {
      "date": "2016-01-26",
      "count": "228"
    },
    {
      "date": "2016-01-27",
      "count": "230"
    },
    {
      "date": "2016-01-28",
      "count": "235"
    },
    {
      "date": "2016-01-29",
      "count": "231"
    },
    {
      "date": "2016-01-31",
      "count": "223"
    },
    {
      "date": "2016-02-01",
      "count": "220"
    },
    {
      "date": "2016-02-02",
      "count": "218"
    },
    {
      "date": "2016-02-03",
      "count": "218"
    },
    {
      "date": "2016-02-06",
      "count": "227"
    },
    {
      "date": "2016-02-07",
      "count": "236"
    },
    {
      "date": "2016-02-08",
      "count": "241"
    },
    {
      "date": "2016-02-10",
      "count": "238"
    },
    {
      "date": "2016-02-11",
      "count": "241"
    },
    {
      "date": "2016-02-12",
      "count": "233"
    },
    {
      "date": "2016-02-13",
      "count": "250"
    },
    {
      "date": "2016-02-14",
      "count": "263"
    }
  ],
  "alex-skorulis": [
    {
      "date": "2015-12-24",
      "count": "52"
    },
    {
      "date": "2015-12-25",
      "count": "51"
    },
    {
      "date": "2015-12-26",
      "count": "51"
    },
    {
      "date": "2015-12-27",
      "count": "52"
    },
    {
      "date": "2015-12-28",
      "count": "51"
    },
    {
      "date": "2015-12-29",
      "count": "51"
    },
    {
      "date": "2016-01-01",
      "count": "47"
    },
    {
      "date": "2016-01-02",
      "count": "50"
    },
    {
      "date": "2016-01-03",
      "count": "54"
    },
    {
      "date": "2016-01-04",
      "count": "51"
    },
    {
      "date": "2016-01-05",
      "count": "48"
    },
    {
      "date": "2016-01-06",
      "count": "47"
    },
    {
      "date": "2016-01-07",
      "count": "46"
    },
    {
      "date": "2016-01-08",
      "count": "46"
    },
    {
      "date": "2016-01-09",
      "count": "46"
    },
    {
      "date": "2016-01-10",
      "count": "46"
    },
    {
      "date": "2016-01-11",
      "count": "47"
    },
    {
      "date": "2016-01-12",
      "count": "49"
    },
    {
      "date": "2016-01-13",
      "count": "47"
    },
    {
      "date": "2016-01-14",
      "count": "49"
    },
    {
      "date": "2016-01-15",
      "count": "49"
    },
    {
      "date": "2016-01-16",
      "count": "49"
    },
    {
      "date": "2016-01-20",
      "count": "49"
    },
    {
      "date": "2016-01-21",
      "count": "50"
    },
    {
      "date": "2016-01-22",
      "count": "49"
    },
    {
      "date": "2016-01-23",
      "count": "51"
    },
    {
      "date": "2016-01-25",
      "count": "50"
    },
    {
      "date": "2016-01-26",
      "count": "49"
    },
    {
      "date": "2016-01-27",
      "count": "51"
    },
    {
      "date": "2016-01-28",
      "count": "52"
    },
    {
      "date": "2016-01-29",
      "count": "51"
    },
    {
      "date": "2016-01-31",
      "count": "50"
    },
    {
      "date": "2016-02-01",
      "count": "48"
    },
    {
      "date": "2016-02-02",
      "count": "51"
    },
    {
      "date": "2016-02-03",
      "count": "52"
    },
    {
      "date": "2016-02-06",
      "count": "54"
    },
    {
      "date": "2016-02-07",
      "count": "55"
    },
    {
      "date": "2016-02-08",
      "count": "54"
    },
    {
      "date": "2016-02-10",
      "count": "52"
    },
    {
      "date": "2016-02-11",
      "count": "51"
    },
    {
      "date": "2016-02-12",
      "count": "51"
    },
    {
      "date": "2016-02-13",
      "count": "50"
    },
    {
      "date": "2016-02-14",
      "count": "50"
    }
  ],
  "askoruli": [
    {
      "date": "2015-12-24",
      "count": "73"
    },
    {
      "date": "2015-12-25",
      "count": "72"
    },
    {
      "date": "2015-12-26",
      "count": "76"
    },
    {
      "date": "2015-12-27",
      "count": "80"
    },
    {
      "date": "2015-12-28",
      "count": "77"
    },
    {
      "date": "2015-12-29",
      "count": "76"
    },
    {
      "date": "2016-01-01",
      "count": "84"
    },
    {
      "date": "2016-01-02",
      "count": "78"
    },
    {
      "date": "2016-01-03",
      "count": "82"
    },
    {
      "date": "2016-01-04",
      "count": "85"
    },
    {
      "date": "2016-01-05",
      "count": "87"
    },
    {
      "date": "2016-01-06",
      "count": "87"
    },
    {
      "date": "2016-01-07",
      "count": "83"
    },
    {
      "date": "2016-01-08",
      "count": "85"
    },
    {
      "date": "2016-01-09",
      "count": "83"
    },
    {
      "date": "2016-01-10",
      "count": "85"
    },
    {
      "date": "2016-01-11",
      "count": "91"
    },
    {
      "date": "2016-01-12",
      "count": "90"
    },
    {
      "date": "2016-01-13",
      "count": "83"
    },
    {
      "date": "2016-01-14",
      "count": "82"
    },
    {
      "date": "2016-01-15",
      "count": "86"
    },
    {
      "date": "2016-01-16",
      "count": "92"
    },
    {
      "date": "2016-01-20",
      "count": "88"
    },
    {
      "date": "2016-01-21",
      "count": "85"
    },
    {
      "date": "2016-01-22",
      "count": "86"
    },
    {
      "date": "2016-01-23",
      "count": "87"
    },
    {
      "date": "2016-01-25",
      "count": "86"
    },
    {
      "date": "2016-01-26",
      "count": "86"
    },
    {
      "date": "2016-01-27",
      "count": "88"
    },
    {
      "date": "2016-01-28",
      "count": "87"
    },
    {
      "date": "2016-01-29",
      "count": "87"
    },
    {
      "date": "2016-01-31",
      "count": "90"
    },
    {
      "date": "2016-02-01",
      "count": "90"
    },
    {
      "date": "2016-02-02",
      "count": "93"
    },
    {
      "date": "2016-02-03",
      "count": "97"
    },
    {
      "date": "2016-02-06",
      "count": "91"
    },
    {
      "date": "2016-02-07",
      "count": "90"
    },
    {
      "date": "2016-02-08",
      "count": "91"
    },
    {
      "date": "2016-02-10",
      "count": "95"
    },
    {
      "date": "2016-02-11",
      "count": "90"
    },
    {
      "date": "2016-02-12",
      "count": "111"
    },
    {
      "date": "2016-02-13",
      "count": "112"
    },
    {
      "date": "2016-02-14",
      "count": "111"
    }
  ]
}